Fanduel_Webscrape/MyApp.py
Fanduel_Webscrape-1.0.14.dist-info/LICENSE
Fanduel_Webscrape-1.0.14.dist-info/METADATA
Fanduel_Webscrape-1.0.14.dist-info/WHEEL
Fanduel_Webscrape-1.0.14.dist-info/entry_points.txt
Fanduel_Webscrape-1.0.14.dist-info/top_level.txt
Fanduel_Webscrape-1.0.14.dist-info/RECORD
