Metadata-Version: 2.1
Name: Fanduel-Webscrape
Version: 1.0.14
Summary: A python script that will webscrape historical NBA Fanduel salary info.
Home-page: https://github.com/nathanhilton/NBAFanduel
Author: Nathan Hilton
Author-email: nathanhilton24@gmail.com
License: UNKNOWN
Platform: UNKNOWN
Classifier: Programming Language :: Python :: 3
Classifier: Programming Language :: Python :: 3.7
Requires-Dist: requests
Requires-Dist: beautifulsoup4 (>=4.0.0)
